{
  "conditions": [
    {
      "type": "forge:mod_loaded",
      "modid": "create"
    },
    {
      "type": "forge:item_exists",
      "item": "ironfurnaces:copper_furnace"
    }
  ],
  "type": "create:mechanical_crafting",
  "acceptMirrored": false,
  "key": {
    "A": {
      "tag": "forge:plates/copper"
    },
    "B": {
      "item": "minecraft:furnace"
    }
  },
  "pattern": [
    " AAA ",
    " ABA ",
    " AAA ",
    "     ",
    "     "
  ],
  "result": {
    "count": 1,
    "item": "ironfurnaces:copper_furnace"
  }
}