{
  "conditions": [
    {
      "type": "forge:mod_loaded",
      "modid": "notenoughwands"
    },
    {
      "type": "forge:item_exists",
      "item": "notenoughwands:building_wand"
    },
    {
      "type": "forge:item_exists",
      "item": "buildinggadgets:construction_paste"
    }
  ],
  "type": "minecraft:smithing",
  "base": {
    "item": "buildinggadgets:construction_paste"
  },
  "addition": {
    "item": "notenoughwands:wand_core"
  },
  "result": {
    "item": "notenoughwands:building_wand"
  }
}