{
  "conditions": [
    {
      "type": "forge:mod_loaded",
      "modid": "create"
    },
    {
      "type": "forge:item_exists",
      "item": "extendedcrafting:the_ultimate_ingot"
    }
  ],
  "type": "create:mixing",
  "heatRequirement": "superheated",
  "ingredients": [
    {
      "item": "extendedcrafting:black_iron_ingot"
    },
    {
      "item": "extendedcrafting:black_iron_ingot"
    },
    {
      "item": "extendedcrafting:redstone_ingot"
    },
    {
      "item": "extendedcrafting:redstone_ingot"
    },
    {
      "item": "extendedcrafting:ender_ingot"
    },
    {
      "item": "extendedcrafting:ender_ingot"
    },
    {
      "item": "extendedcrafting:enhanced_ender_ingot"
    },
    {
      "item": "extendedcrafting:enhanced_ender_ingot"
    },
    {
      "item": "extendedcrafting:crystaltine_ingot"
    },
    {
      "item": "extendedcrafting:crystaltine_ingot"
    }
  ],
  "results": [
    {
      "item": "extendedcrafting:the_ultimate_ingot"
    }
  ]
}