{
  "conditions": [
    {
      "type": "forge:mod_loaded",
      "modid": "torchmaster"
    },
    {
      "type": "forge:item_exists",
      "item": "torchmaster:megatorch"
    },
    {
      "type": "forge:item_exists",
      "item": "reliquary:sojourner_staff"
    }
  ],
  "type": "minecraft:crafting_shaped",
  "key": {
    "T": {
      "item": "reliquary:sojourner_staff"
    },
    "G": {
      "tag": "forge:storage_blocks/gold"
    },
    "D": {
      "tag": "forge:storage_blocks/diamond"
    },
    "L": {
      "tag": "minecraft:logs"
    }
  },
  "pattern": [
    "TTT",
    "GLG",
    "DLD"
  ],
  "result": {
    "item": "torchmaster:megatorch"
  }
}