{
  "conditions": [
    {
      "type": "forge:mod_loaded",
      "modid": "mekanism"
    },
    {
      "type": "forge:item_exists",
      "item": "mekanism:teleporter"
    },
    {
      "type": "forge:item_exists",
      "item": "modernrecipes:compressed_iron_plate"
    }
  ],
  "type": "minecraft:crafting_shaped",
  "key": {
    "A": {
      "item": "mekanism:teleportation_core"
    },
    "B": {
      "tag": "forge:circuits/basic"
    },
    "C": {
      "item": "modernrecipes:compressed_iron_plate"
    },
    "D": {
      "item": "mekanism:steel_casing"
    }
  },
  "pattern": [
    "BCB",
    "CAC",
    "BDB"
  ],
  "result": {
    "item": "mekanism:teleporter"
  }
}